agentic_reliability_framework/__init__.py
agentic_reliability_framework/__version__.py
agentic_reliability_framework/app.py
agentic_reliability_framework/cli.py
agentic_reliability_framework/config.py
agentic_reliability_framework/healing_policies.py
agentic_reliability_framework/lazy.py
agentic_reliability_framework/models.py
agentic_reliability_framework/arf_core/__init__.py
agentic_reliability_framework/arf_core/constants.py
agentic_reliability_framework/arf_core/config/oss_config.py
agentic_reliability_framework/arf_core/engine/oss_mcp_client.py
agentic_reliability_framework/arf_core/models/__init__.py
agentic_reliability_framework/arf_core/models/healing_intent.py
agentic_reliability_framework/data/incident_texts.json
agentic_reliability_framework/data/incident_vectors.index
agentic_reliability_framework/engine/__init__.py
agentic_reliability_framework/engine/anomaly.py
agentic_reliability_framework/engine/business.py
agentic_reliability_framework/engine/engine_factory.py
agentic_reliability_framework/engine/interfaces.py
agentic_reliability_framework/engine/mcp_client.py
agentic_reliability_framework/engine/mcp_factory.py
agentic_reliability_framework/engine/mcp_server.py
agentic_reliability_framework/engine/oss_mcp_client_wrapper.py
agentic_reliability_framework/engine/predictive.py
agentic_reliability_framework/engine/reliability.py
agentic_reliability_framework/engine/v3_reliability.py
agentic_reliability_framework/memory/__init__.py
agentic_reliability_framework/memory/constants.py
agentic_reliability_framework/memory/enhanced_faiss.py
agentic_reliability_framework/memory/faiss_index.py
agentic_reliability_framework/memory/models.py
agentic_reliability_framework/memory/rag_graph.py
agentic_reliability_framework-3.3.9.dist-info/licenses/LICENSE
agentic_reliability_framework-3.3.9.dist-info/METADATA
agentic_reliability_framework-3.3.9.dist-info/WHEEL
agentic_reliability_framework-3.3.9.dist-info/top_level.txt
agentic_reliability_framework-3.3.9.dist-info/RECORD
