Metadata-Version: 2.4
Name: agentic-reliability-framework
Version: 3.3.9
Summary: Agentic Reliability Framework (OSS Edition): Enterprise-grade multi-agent AI for infrastructure reliability monitoring and advisory-only self-healing.
Author-email: Juan Petter <ai@petterjuan.com>
License: Apache-2.0
Project-URL: Homepage, https://github.com/petterjuan/agentic-reliability-framework
Project-URL: Repository, https://github.com/petterjuan/agentic-reliability-framework
Project-URL: Documentation, https://github.com/petterjuan/agentic-reliability-framework/tree/main/docs
Project-URL: Live Demo, https://huggingface.co/spaces/petter2025/agentic-reliability-framework
Project-URL: Enterprise, https://arf.dev/enterprise
Keywords: agentic-ai,ai-infrastructure,reliability-engineering,self-healing-systems,observability,rag,faiss,mcp,site-reliability-engineering,autonomous-systems
Classifier: Development Status :: 5 - Production/Stable
Classifier: Intended Audience :: Developers
Classifier: Intended Audience :: System Administrators
Classifier: License :: OSI Approved :: Apache Software License
Classifier: Operating System :: OS Independent
Classifier: Programming Language :: Python :: 3
Classifier: Programming Language :: Python :: 3.10
Classifier: Programming Language :: Python :: 3.11
Classifier: Programming Language :: Python :: 3.12
Classifier: Topic :: Software Development :: Libraries :: Python Modules
Classifier: Topic :: System :: Monitoring
Classifier: Topic :: System :: Recovery Tools
Classifier: Typing :: Typed
Requires-Python: >=3.10
License-File: LICENSE
Requires-Dist: pydantic>=2.0.0
Requires-Dist: typing-extensions>=4.8
Requires-Dist: numpy>=1.24.0
Requires-Dist: pandas>=2.0.0
Requires-Dist: faiss-cpu>=1.7.0
Requires-Dist: httpx>=0.25.0
Requires-Dist: requests>=2.31.0
Requires-Dist: circuitbreaker>=1.4.0
Requires-Dist: atomicwrites>=1.4.0
Requires-Dist: gradio>=4.19.0
Provides-Extra: dev
Requires-Dist: pytest>=7.0.0; extra == "dev"
Requires-Dist: pytest-asyncio>=0.21.0; extra == "dev"
Requires-Dist: pytest-cov>=4.0.0; extra == "dev"
Requires-Dist: mypy>=1.0.0; extra == "dev"
Requires-Dist: ruff>=0.1.0; extra == "dev"
Requires-Dist: black>=23.0.0; extra == "dev"
Requires-Dist: types-requests; extra == "dev"
Requires-Dist: types-PyYAML; extra == "dev"
Dynamic: license-file
